MANIFEST.in
README.md
setup.py
freeflow/__init__.py
freeflow.egg-info/PKG-INFO
freeflow.egg-info/SOURCES.txt
freeflow.egg-info/dependency_links.txt
freeflow.egg-info/not-zip-safe
freeflow.egg-info/requires.txt
freeflow.egg-info/top_level.txt
freeflow/__pycache__/__init__.cpython-36.pyc
freeflow/bin/freeflow
freeflow/core/__init__.py
freeflow/core/cli.py
freeflow/core/dag_loader.py
freeflow/core/log.py
freeflow/core/security.py
freeflow/core/__pycache__/__init__.cpython-36.pyc
freeflow/core/__pycache__/cli.cpython-36.pyc
freeflow/core/__pycache__/dag_loader.cpython-36.pyc
freeflow/core/__pycache__/log.cpython-36.pyc
freeflow/core/__pycache__/security.cpython-36.pyc
freeflow/core/deployment/__init__.py
freeflow/core/deployment/base.py
freeflow/core/deployment/composer.py
freeflow/core/deployment/direct.py
freeflow/core/deployment/__pycache__/__init__.cpython-36.pyc
freeflow/core/deployment/__pycache__/base.cpython-36.pyc
freeflow/core/deployment/__pycache__/composer.cpython-36.pyc
freeflow/core/deployment/__pycache__/direct.cpython-36.pyc
freeflow/core/initialization/__init__.py
freeflow/core/initialization/direct.py
freeflow/core/initialization/__pycache__/__init__.cpython-36.pyc
freeflow/core/initialization/__pycache__/direct.cpython-36.pyc
freeflow/core/tests/__init__.py
freeflow/core/tests/dag.py
freeflow/core/tests/__pycache__/__init__.cpython-36.pyc
freeflow/core/tests/__pycache__/dag.cpython-36.pyc
freeflow/core/tests/operator/__init__.py
freeflow/core/tests/operator/bigquery.py
freeflow/core/tests/operator/__pycache__/__init__.cpython-36.pyc
freeflow/core/tests/operator/__pycache__/bigquery.cpython-36.pyc
freeflow/core/tests/sensor/__init__.py
freeflow/core/tests/sensor/externaltask.py
freeflow/core/tests/sensor/__pycache__/__init__.cpython-36.pyc
freeflow/core/tests/sensor/__pycache__/externaltask.cpython-36.pyc
freeflow/template/__init__.py.tpl
freeflow/template/default.cfg
freeflow/template/manage.py.tpl
freeflow/template/data/conf.cfg
freeflow/template/data/conn.json
freeflow/template/data/pool.json
freeflow/template/data/vars.json