Metadata-Version: 1.0
Name: freeflow
Version: 0.1.11
Summary: Airflow development and deployment, simplified.
Home-page: http://github.com/feryandi/freeflow
Author: Feryandi Nurdiantoro
Author-email: feryandi.n@gmail.com
License: Apache License 2.0
Platform: UNKNOWN
